pegasustools/__init__.py
pegasustools/_version.py
pegasustools/_version.pyi
pegasustools/loading_hst.py
pegasustools/loading_nbf.py
pegasustools/loading_spectra.py
pegasustools/loading_traces.py
pegasustools/loading_tracks.py
pegasustools/mpl_setup.py
pegasustools/pegasus_style.mplstyle
pegasustools/pt_logging.py
pegasustools/py.typed
pegasustools-1.0.0.dist-info/METADATA
pegasustools-1.0.0.dist-info/WHEEL
pegasustools-1.0.0.dist-info/licenses/LICENSE
pegasustools-1.0.0.dist-info/RECORD
