Metadata-Version: 2.4
Name: pegasustools
Version: 1.0.0
Summary: Analysis package for the Pegasus PIC code.
Project-URL: Homepage, https://github.com/PegasusPIC/pegasustools
Project-URL: Bug Tracker, https://github.com/PegasusPIC/pegasustools/issues
Project-URL: Discussions, https://github.com/PegasusPIC/pegasustools/discussions
Project-URL: Changelog, https://github.com/PegasusPIC/pegasustools/releases
Author-email: Robert Caddy <rcaddy@princeton.edu>
License-File: LICENSE
Classifier: Development Status :: 1 - Planning
Classifier: Intended Audience :: Developers
Classifier: Intended Audience :: Science/Research
Classifier: License :: OSI Approved :: MIT License
Classifier: Operating System :: OS Independent
Classifier: Programming Language :: Python
Classifier: Programming Language :: Python :: 3
Classifier: Programming Language :: Python :: 3 :: Only
Classifier: Programming Language :: Python :: 3.13
Classifier: Topic :: Scientific/Engineering
Classifier: Topic :: Scientific/Engineering :: Astronomy
Classifier: Topic :: Scientific/Engineering :: Physics
Classifier: Typing :: Typed
Requires-Python: >=3.13
Requires-Dist: matplotlib>=3.10
Requires-Dist: numpy>=2.2
Requires-Dist: polars-u64-idx[numpy]>=1.29
Provides-Extra: dev
Requires-Dist: pytest-cov>=6; extra == 'dev'
Requires-Dist: pytest>=8; extra == 'dev'
Provides-Extra: docs
Requires-Dist: furo>=2023.08.17; extra == 'docs'
Requires-Dist: ipykernel; extra == 'docs'
Requires-Dist: myst-parser>=0.13; extra == 'docs'
Requires-Dist: nbsphinx>=0.9.7; extra == 'docs'
Requires-Dist: pytest>=8; extra == 'docs'
Requires-Dist: sphinx-autodoc-typehints; extra == 'docs'
Requires-Dist: sphinx-copybutton; extra == 'docs'
Requires-Dist: sphinx>=7.0; extra == 'docs'
Provides-Extra: test
Requires-Dist: pytest-cov>=6; extra == 'test'
Requires-Dist: pytest>=8; extra == 'test'
